rtm_mcp/__init__.py
rtm_mcp/client.py
rtm_mcp/config.py
rtm_mcp/exceptions.py
rtm_mcp/response_builder.py
rtm_mcp/server.py
rtm_mcp/types.py
rtm_mcp/scripts/__init__.py
rtm_mcp/scripts/setup_auth.py
rtm_mcp/tools/__init__.py
rtm_mcp/tools/lists.py
rtm_mcp/tools/notes.py
rtm_mcp/tools/tasks.py
rtm_mcp/tools/utilities.py
rtm_mcp-1.0.0.dist-info/METADATA
rtm_mcp-1.0.0.dist-info/WHEEL
rtm_mcp-1.0.0.dist-info/entry_points.txt
rtm_mcp-1.0.0.dist-info/licenses/LICENSE
rtm_mcp-1.0.0.dist-info/RECORD
