Metadata-Version: 2.4
Name: rtm-mcp
Version: 1.0.0
Summary: Remember The Milk MCP Server - Full API coverage for Claude
Project-URL: Homepage, https://github.com/ljadach/rtm-mcp
Project-URL: Repository, https://github.com/ljadach/rtm-mcp
Project-URL: Issues, https://github.com/ljadach/rtm-mcp/issues
Author: ljadach
License: MIT
License-File: LICENSE
Keywords: ai,claude,mcp,remember-the-milk,rtm,tasks
Classifier: Development Status :: 4 - Beta
Classifier: Intended Audience :: Developers
Classifier: License :: OSI Approved :: MIT License
Classifier: Programming Language :: Python :: 3
Classifier: Programming Language :: Python :: 3.11
Classifier: Programming Language :: Python :: 3.12
Requires-Python: >=3.11
Requires-Dist: fastmcp>=2.0.0
Requires-Dist: httpx>=0.27.0
Requires-Dist: pydantic-settings>=2.0.0
Requires-Dist: pydantic>=2.0.0
Provides-Extra: dev
Requires-Dist: pyright>=1.1.380; extra == 'dev'
Requires-Dist: pytest-asyncio>=0.24.0; extra == 'dev'
Requires-Dist: pytest-cov>=5.0.0; extra == 'dev'
Requires-Dist: pytest>=8.0.0; extra == 'dev'
Requires-Dist: respx>=0.21.0; extra == 'dev'
Requires-Dist: ruff>=0.5.0; extra == 'dev'
